tomlini/__init__.py
tomlini/example.py
tomlini-1.0.1.dist-info/LICENSE
tomlini-1.0.1.dist-info/METADATA
tomlini-1.0.1.dist-info/WHEEL
tomlini-1.0.1.dist-info/top_level.txt
tomlini-1.0.1.dist-info/RECORD
