Metadata-Version: 2.1
Name: tomlini
Version: 1.0.1
Summary: A tiny library for initializing objects from TOML files
Author-email: "Levi C. Schanding" <levischanding1@gmail.com>
Project-URL: Homepage, https://github.com/The-Ranger22/tomlini
Project-URL: Bug Tracker, https://github.com/The-Ranger22/tomlini/issues
Classifier: Programming Language :: Python :: 3
Classifier: License :: OSI Approved :: MIT License
Classifier: Operating System :: OS Independent
Requires-Python: >=3.11
License-File: LICENSE
